fao56_model/__init__.py
fao56_model/crop_calendar.py
fao56_model/crop_simulation.py
fao56_model/data/crops.csv
fao56_model/data/soils.csv
fao56_model/data_models/__init__.py
fao56_model/data_models/climate.py
fao56_model/data_models/crop.py
fao56_model/data_models/simulation_state.py
fao56_model/data_models/soil.py
fao56_model/databases.py
fao56_model/planted_crop.py
fao56_model/py.typed
fao56_model/utils.py
fao56_model-0.1.9.dist-info/METADATA
fao56_model-0.1.9.dist-info/WHEEL
fao56_model-0.1.9.dist-info/RECORD
