Metadata-Version: 2.1
Name: fao56-model
Version: 0.1.9
Summary: A Python package for FAO-56 model calculations.
License: MIT
Author: Stephan Smit
Author-email: stephansmit@hotmail.com
Requires-Python: >=3.11,<4.0
Classifier: License :: OSI Approved :: MIT License
Classifier: Programming Language :: Python :: 3
Classifier: Programming Language :: Python :: 3.11
Classifier: Programming Language :: Python :: 3.12
Requires-Dist: datetimerange (>=2.2.0,<3.0.0)
Requires-Dist: matplotlib (>=3.8.3,<4.0.0)
Requires-Dist: pandas (>=2.2.0,<3.0.0)
Requires-Dist: pydantic (>=2.6.1,<3.0.0)
